webio_jupyter_extension/__init__.py
webio_jupyter_extension/_version.py
webio_jupyter_extension/serverextension.py
webio_jupyter_extension/labextension/build_log.json
webio_jupyter_extension/labextension/package.json
webio_jupyter_extension/labextension/static/dist_labextension_js.427f6e3abbcd6b9d9bce.js
webio_jupyter_extension/labextension/static/dist_labextension_js.427f6e3abbcd6b9d9bce.js.map
webio_jupyter_extension/labextension/static/remoteEntry.aadd79f071b43ec6d4df.js
webio_jupyter_extension/labextension/static/remoteEntry.aadd79f071b43ec6d4df.js.map
webio_jupyter_extension/labextension/static/style.js
webio_jupyter_extension/nbextension/nbextension.js
webio_jupyter_extension-0.1.0.data/data/etc/jupyter/jupyter_notebook_config.d/webio_jupyter_extension.json
webio_jupyter_extension-0.1.0.data/data/etc/jupyter/jupyter_server_config.d/webio_jupyter_extension.json
webio_jupyter_extension-0.1.0.data/data/etc/jupyter/nbconfig/notebook.d/webio-jupyter-nbextension.json
webio_jupyter_extension-0.1.0.data/data/share/jupyter/labextensions/webio-jupyterlab-provider/build_log.json
webio_jupyter_extension-0.1.0.data/data/share/jupyter/labextensions/webio-jupyterlab-provider/install.json
webio_jupyter_extension-0.1.0.data/data/share/jupyter/labextensions/webio-jupyterlab-provider/package.json
webio_jupyter_extension-0.1.0.data/data/share/jupyter/labextensions/webio-jupyterlab-provider/static/dist_labextension_js.427f6e3abbcd6b9d9bce.js
webio_jupyter_extension-0.1.0.data/data/share/jupyter/labextensions/webio-jupyterlab-provider/static/dist_labextension_js.427f6e3abbcd6b9d9bce.js.map
webio_jupyter_extension-0.1.0.data/data/share/jupyter/labextensions/webio-jupyterlab-provider/static/remoteEntry.aadd79f071b43ec6d4df.js
webio_jupyter_extension-0.1.0.data/data/share/jupyter/labextensions/webio-jupyterlab-provider/static/remoteEntry.aadd79f071b43ec6d4df.js.map
webio_jupyter_extension-0.1.0.data/data/share/jupyter/labextensions/webio-jupyterlab-provider/static/style.js
webio_jupyter_extension-0.1.0.dist-info/LICENSE
webio_jupyter_extension-0.1.0.dist-info/METADATA
webio_jupyter_extension-0.1.0.dist-info/WHEEL
webio_jupyter_extension-0.1.0.dist-info/top_level.txt
webio_jupyter_extension-0.1.0.dist-info/RECORD
